requests_ntlm/__init__.py
requests_ntlm/requests_ntlm.py
requests_ntlm-1.2.0.dist-info/LICENSE
requests_ntlm-1.2.0.dist-info/METADATA
requests_ntlm-1.2.0.dist-info/WHEEL
requests_ntlm-1.2.0.dist-info/top_level.txt
requests_ntlm-1.2.0.dist-info/RECORD
