Metadata-Version: 2.1
Name: requests_ntlm
Version: 1.2.0
Summary: This package allows for HTTP NTLM authentication using the requests library.
Home-page: https://github.com/requests/requests-ntlm
Author: Ben Toews
Author-email: mastahyeti@gmail.com
License: ISC
Classifier: Development Status :: 4 - Beta
Classifier: Intended Audience :: Developers
Classifier: Programming Language :: Python
Classifier: Programming Language :: Python :: 3
Classifier: Programming Language :: Python :: 3.7
Classifier: Programming Language :: Python :: 3.8
Classifier: Programming Language :: Python :: 3.9
Classifier: Programming Language :: Python :: 3.10
Classifier: Programming Language :: Python :: 3.11
Classifier: License :: OSI Approved :: ISC License (ISCL)
Requires-Python: >=3.7
License-File: LICENSE
